{"query": "query ShopInfo {\n  shop {\n    countries {\n      country\n      code\n      __typename\n    }\n    defaultCountry {\n      code\n      country\n      __typename\n    }\n    defaultCurrency\n    defaultWeightUnit\n    displayGrossPrices\n    domain {\n      host\n      url\n      __typename\n    }\n    languages {\n      code\n      language\n      __typename\n    }\n    includeTaxesInPrices\n    name\n    trackInventoryByDefault\n    permissions {\n      code\n      name\n      __typename\n    }\n    __typename\n  }\n}\n", "variables": {}, "operationName": "ShopInfo", "timesCalled": 8, "createdAt": "2021-09-04 12:44:56.745338+00:00", "updatedAt": "2021-09-05 13:38:01.796072+00:00"}